netzeus_cli/__init__.py
netzeus_cli/cli.py
netzeus_cli/settings/__init__.py
netzeus_cli-0.0.1.dist-info/METADATA
netzeus_cli-0.0.1.dist-info/WHEEL
netzeus_cli-0.0.1.dist-info/entry_points.txt
netzeus_cli-0.0.1.dist-info/top_level.txt
netzeus_cli-0.0.1.dist-info/RECORD
