Metadata-Version: 2.1
Name: netzeus-cli
Version: 0.0.1
Summary: CLI Tool built by Network Engineers for Network Engineers
Requires-Dist: click (==8.0.4)
Requires-Dist: click-plugins (==1.1.1)
Requires-Dist: python-dotenv (==0.19.2)
Requires-Dist: loguru (==0.6.0)
Requires-Dist: requests (==2.28.1)
Requires-Dist: pydantic (==1.10.2)
